nextrade/__init__.py
nextrade/nxt.py
nextrade-0.1.7.dist-info/METADATA
nextrade-0.1.7.dist-info/WHEEL
nextrade-0.1.7.dist-info/top_level.txt
nextrade-0.1.7.dist-info/RECORD
