Metadata-Version: 2.1
Name: nextrade
Version: 0.1.7
Summary: Trade volume analysis tool
Home-page: https://github.com/nextrade/library
Author: nxt
Author-email: nxt@nextrade.com
Classifier: Programming Language :: Python :: 3
Classifier: License :: OSI Approved :: MIT License
Classifier: Operating System :: OS Independent
Requires-Python: >=3.7
Requires-Dist: numpy
Requires-Dist: pandas
Requires-Dist: requests
Requires-Dist: plotly
